Workbook

Sheet Raw_Sales_Data
A1: Product ID | B1: Product Category | C1: Product Subcategory | D1: Product Name | E1: Order Date | F1: Month | G1: Year | H1: Wholesale Price | I1: Retail Price | J1: Order Quantity | K1: Total (Before Tax) | L1: Tax Due | M1: Order Total | N1: Payment Method | O1: Order Status | P1: Order ID | Q1: Customer ID | R1: Product Description | S1: Product Size | T1: Product Weight | U1: Calculate Month | V1: Calculate year | W1: Calculate Order Total | X1: Calculate Tax Due
A2: 1001 | B2: MOUNTAIN BIKES | C2: Cross Country | D2: Trailblazer 1000 | E2: 44562 | H2: 840 | I2: 1200 | J2: 2 | M2: =K2+L2 -> 0 | N2: Credit Card | O2: Shipped | P2: 2001 | Q2: 3001 | R2: Lightweight and versatile | S2: M | T2: 25 | U2: =MONTH(E2) -> 1 | V2: =YEAR(E2) -> 2022 | W2: =I2 * J2 -> 2400 | X2: =IF(W2>2000,W2*0.05,0) -> 120
A3: 1002 | B3: MOUNTAIN BIKES | C3: Cross Country | D3: Urbaneco 1000 | E3: 44562 | H3: 1460 | I3: 2000 | J3: 2 | M3: =K3+L3 -> 0 | N3: Credit Card | O3: Shipped | P3: 2061 | Q3: 3061 | R3: Eco-friendly electric city bike | S3: M | T3: 35 | U3: =MONTH(E3) -> 1 | V3: =YEAR(E3) -> 2022 | W3: =I3 * J3 -> 4000 | X3: =IF(W3>2000,W3*0.05,0) -> 200
A4: 1003 | B4: ROAD BIKES | C4: Racing | D4: Trailblazer 1000 | E4: 44562 | H4: 840 | I4: 1200 | J4: 2 | M4: =K4+L4 -> 0 | N4: Credit Card | O4: Shipped | P4: 2001 | Q4: 3001 | R4: Lightweight and versatile | S4: M | T4: 25 | U4: =MONTH(E4) -> 1 | V4: =YEAR(E4) -> 2022 | W4: =I4 * J4 -> 2400 | X4: =IF(W4>2000,W4*0.05,0) -> 120
A5: 1004 | B5: ROAD BIKES | C5: Racing | D5: Trailblazer 2000 | E5: 44563 | H5: 1050 | I5: 1500 | J5: 1 | M5: =K5+L5 -> 0 | N5: PayPal | O5: Processing | P5: 2002 | Q5: 3002 | R5: High-performance mountain bike | S5: L | T5: 22 | U5: =MONTH(E5) -> 1 | V5: =YEAR(E5) -> 2022 | W5: =I5 * J5 -> 1500 | X5: =IF(W5>2000,W5*0.05,0) -> 0
A6: 1005 | B6: TOURING BIKES | C6: Long Distance | D6: Urbaneco 2000 | E6: 44563 | H6: 1825 | I6: 2500 | J6: 1 | M6: =K6+L6 -> 0 | N6: PayPal | O6: Processing | P6: 2062 | Q6: 3062 | R6: High-performance electric city bike | S6: L | T6: 33 | U6: =MONTH(E6) -> 1 | V6: =YEAR(E6) -> 2022 | W6: =I6 * J6 -> 2500 | X6: =IF(W6>2000,W6*0.05,0) -> 125
A7: 1006 | B7: TOURING BIKES | C7: Long Distance | D7: Trailblazer 2000 | E7: 44563 | H7: 1050 | I7: 1500 | J7: 1 | M7: =K7+L7 -> 0 | N7: PayPal | O7: Processing | P7: 2002 | Q7: 3002 | R7: High-performance mountain bike | S7: L | T7: 22 | U7: =MONTH(E7) -> 1 | V7: =YEAR(E7) -> 2022 | W7: =I7 * J7 -> 1500 | X7: =IF(W7>2000,W7*0.05,0) -> 0
A8: 1007 | B8: MOUNTAIN BIKES | C8: Downhill | D8: Speedmaster 1000 | E8: 44564 | H8: 1260 | I8: 1800 | J8: 3 | M8: =K8+L8 -> 0 | N8: Credit Card | O8: Cancelled | P8: 2003 | Q8: 3003 | R8: Agile and aerodynamic road bike | S8: M | T8: 18 | U8: =MONTH(E8) -> 1 | V8: =YEAR(E8) -> 2022 | W8: =I8 * J8 -> 5400 | X8: =IF(W8>2000,W8*0.05,0) -> 270
A9: 1008 | B9: MOUNTAIN BIKES | C9: Downhill | D9: Speedmaster 1000 | E9: 44564 | H9: 1260 | I9: 1800 | J9: 3 | M9: =K9+L9 -> 0 | N9: Credit Card | O9: Cancelled | P9: 2003 | Q9: 3003 | R9: Agile and aerodynamic road bike | S9: M | T9: 18 | U9: =MONTH(E9) -> 1 | V9: =YEAR(E9) -> 2022 | W9: =I9 * J9 -> 5400 | X9: =IF(W9>2000,W9*0.05,0) -> 270
A10: 1009 | B10: MOUNTAIN BIKES | C10: Trail | D10: Speedmaster 2000 | E10: 44565 | H10: 1470 | I10: 2100 | J10: 1 | M10: =K10+L10 -> 0 | N10: Credit Card | O10: Shipped | P10: 2004 | Q10: 3004 | R10: Premium racing road bike | S10: L | T10: 16 | U10: =MONTH(E10) -> 1 | V10: =YEAR(E10) -> 2022 | W10: =I10 * J10 -> 2100 | X10: =IF(W10>2000,W10*0.05,0) -> 105
A11: 1010 | B11: MOUNTAIN BIKES | C11: Trail | D11: Speedmaster 2000 | E11: 44565 | H11: 1470 | I11: 2100 | J11: 1 | M11: =K11+L11 -> 0 | N11: Credit Card | O11: Shipped | P11: 2004 | Q11: 3004 | R11: Premium racing road bike | S11: L | T11: 16 | U11: =MONTH(E11) -> 1 | V11: =YEAR(E11) -> 2022 | W11: =I11 * J11 -> 2100 | X11: =IF(W11>2000,W11*0.05,0) -> 105
A12: 1011 | B12: ROAD BIKES | C12: Touring | D12: Explorer 1000 | E12: 44566 | H12: 897 | I12: 1300 | J12: 2 | M12: =K12+L12 -> 0 | N12: PayPal | O12: Processing | P12: 2005 | Q12: 3005 | R12: Comfortable and durable touring bike | S12: M | T12: 27 | U12: =MONTH(E12) -> 1 | V12: =YEAR(E12) -> 2022 | W12: =I12 * J12 -> 2600 | X12: =IF(W12>2000,W12*0.05,0) -> 130
A13: 1012 | B13: ROAD BIKES | C13: Touring | D13: Explorer 1000 | E13: 44566 | H13: 897 | I13: 1300 | J13: 2 | M13: =K13+L13 -> 0 | N13: PayPal | O13: Processing | P13: 2005 | Q13: 3005 | R13: Comfortable and durable touring bike | S13: M | T13: 27 | U13: =MONTH(E13) -> 1 | V13: =YEAR(E13) -> 2022 | W13: =I13 * J13 -> 2600 | X13: =IF(W13>2000,W13*0.05,0) -> 130
... A246: 1245 | B246: TOURING BIKES | C246: Folding | D246: Enduromaster 2000 | E246: 45013 | H246: 1872 | I246: 2600 | J246: 1 | M246: =K246+L246 -> 0 | N246: Credit Card | O246: Processing | P246: 2028 | Q246: 3028 | R246: High-performance enduro mountain bike | S246: L | T246: 28 | U246: =MONTH(E246) -> 3 | V246: =YEAR(E246) -> 2023 | W246: =I246 * J246 -> 2600 | X246: =IF(W246>2000,W246*0.05,0) -> 130

Sheet Executive_Summary
A4: TOTAL Q1 SALES
A5: 2022 Sales | B5: =SUMIFS( Raw_Sales_Data!$W$2:$W$246,Raw_Sales_Data!$V$2:$V$246, 2022,Raw_Sales_Data!$U$2:$U$246, "<=3" ) -> 316600
A6: 2023 Sales | B6: =SUMIFS( Raw_Sales_Data!$W$2:$W$246,Raw_Sales_Data!$V$2:$V$246, 2023,Raw_Sales_Data!$U$2:$U$246, "<=3" ) -> 435100
A7: % Increase | B7: =(B6-B5)/B5 -> 0.37428932
A10: Q1 MONTHLY TOTALS
A11: Month | B11: 2022 | C11: 2023 | D11: % Increase
A12: January | B12: =SUMIFS( Raw_Sales_Data!$W$2:$W$246,Raw_Sales_Data!$V$2:$V$246, 2022,Raw_Sales_Data!$U$2:$U$246,1 ) -> 97300 | C12: =SUMIFS( Raw_Sales_Data!$W$2:$W$246,Raw_Sales_Data!$V$2:$V$246, 2023,Raw_Sales_Data!$U$2:$U$246,1 ) -> 137600 | D12: =(C12-B12)/B12 -> 0.41418294
A13: February | B13: =SUMIFS( Raw_Sales_Data!$W$2:$W$246,Raw_Sales_Data!$V$2:$V$246, 2022,Raw_Sales_Data!$U$2:$U$246,2 ) -> 108600 | C13: =SUMIFS( Raw_Sales_Data!$W$2:$W$246,Raw_Sales_Data!$V$2:$V$246, 2023,Raw_Sales_Data!$U$2:$U$246,2 ) -> 139500 | D13: =(C13-B13)/B13 -> 0.28453039
A14: March | B14: =SUMIFS( Raw_Sales_Data!$W$2:$W$246,Raw_Sales_Data!$V$2:$V$246, 2022,Raw_Sales_Data!$U$2:$U$246,3 ) -> 110700 | C14: =SUMIFS( Raw_Sales_Data!$W$2:$W$246,Raw_Sales_Data!$V$2:$V$246, 2023,Raw_Sales_Data!$U$2:$U$246,3 ) -> 158000 | D14: =(C14-B14)/B14 -> 0.42728094

Sheet Executive_Charts
